{
  "node": {
    "60ee3c9a521f020f597df6fb8b481da98d5ea02650": {
      "workers": {
        "app/(public)/team/page": {
          "moduleId": 75708,
          "async": false,
          "exportedName": "createTeamAction",
          "filename": "features/teams/actions.ts"
        }
      },
      "layer": {
        "app/(public)/team/page": "action-browser"
      },
      "exportedName": "createTeamAction",
      "filename": "features/teams/actions.ts"
    },
    "40961f5099a8b08ebca8265db9899a44d7632debdb": {
      "workers": {
        "app/(public)/team/page": {
          "moduleId": 75708,
          "async": false,
          "exportedName": "joinTeamAction",
          "filename": "features/teams/actions.ts"
        }
      },
      "layer": {
        "app/(public)/team/page": "action-browser"
      },
      "exportedName": "joinTeamAction",
      "filename": "features/teams/actions.ts"
    },
    "0035b0506cd97756c9613d10ea1b09eeb981781668": {
      "workers": {
        "app/(public)/team/page": {
          "moduleId": 75708,
          "async": false,
          "exportedName": "leaveTeamAction",
          "filename": "features/teams/actions.ts"
        }
      },
      "layer": {
        "app/(public)/team/page": "action-browser"
      },
      "exportedName": "leaveTeamAction",
      "filename": "features/teams/actions.ts"
    },
    "40733ef97ae2e716dbb5e92ac7fa3482850a4cea1b": {
      "workers": {
        "app/(public)/team/page": {
          "moduleId": 75708,
          "async": false,
          "exportedName": "kickPlayerAction",
          "filename": "features/teams/actions.ts"
        }
      },
      "layer": {
        "app/(public)/team/page": "action-browser"
      },
      "exportedName": "kickPlayerAction",
      "filename": "features/teams/actions.ts"
    },
    "00f46bb504cf67e0000a50bb0a4d04fd76ba506183": {
      "workers": {
        "app/(public)/team/page": {
          "moduleId": 75708,
          "async": false,
          "exportedName": "getMyTeamData",
          "filename": "features/teams/actions.ts"
        }
      },
      "layer": {
        "app/(public)/team/page": "action-browser"
      },
      "exportedName": "getMyTeamData",
      "filename": "features/teams/actions.ts"
    },
    "405feb67170f1b8697a149f6693f28424a180e26cb": {
      "workers": {
        "app/(public)/team/page": {
          "moduleId": 75708,
          "async": false,
          "exportedName": "updateTeamInfoAction",
          "filename": "features/teams/actions.ts"
        }
      },
      "layer": {
        "app/(public)/team/page": "action-browser"
      },
      "exportedName": "updateTeamInfoAction",
      "filename": "features/teams/actions.ts"
    },
    "40c81f7737738f4cacec49b5c63bf01ee09536f3ab": {
      "workers": {
        "app/(public)/team/page": {
          "moduleId": 75708,
          "async": false,
          "exportedName": "updatePlayerLineupRoleAction",
          "filename": "features/teams/actions.ts"
        }
      },
      "layer": {
        "app/(public)/team/page": "action-browser"
      },
      "exportedName": "updatePlayerLineupRoleAction",
      "filename": "features/teams/actions.ts"
    },
    "00dfc66d618db3e5dfd22af3fd782125532f10324e": {
      "workers": {
        "app/(public)/team/page": {
          "moduleId": 75708,
          "async": false,
          "exportedName": "toggleRecruitmentAction",
          "filename": "features/teams/actions.ts"
        }
      },
      "layer": {
        "app/(public)/team/page": "action-browser"
      },
      "exportedName": "toggleRecruitmentAction",
      "filename": "features/teams/actions.ts"
    },
    "00ec7e4f9c12b1ce5d907259c90cb6990d08c7e7cd": {
      "workers": {
        "app/(public)/team/page": {
          "moduleId": 75708,
          "async": false,
          "exportedName": "regenerateInviteCodeAction",
          "filename": "features/teams/actions.ts"
        }
      },
      "layer": {
        "app/(public)/team/page": "action-browser"
      },
      "exportedName": "regenerateInviteCodeAction",
      "filename": "features/teams/actions.ts"
    },
    "4094a415d52f23ffeaf08a854f70a5d620092812b5": {
      "workers": {
        "app/(public)/team/page": {
          "moduleId": 75708,
          "async": false,
          "exportedName": "toggleTeamReadyAction",
          "filename": "features/teams/actions.ts"
        }
      },
      "layer": {
        "app/(public)/team/page": "action-browser"
      },
      "exportedName": "toggleTeamReadyAction",
      "filename": "features/teams/actions.ts"
    },
    "40662a6edcc00a613ba70a0b0d12e5331cb396cd08": {
      "workers": {
        "app/(public)/team/page": {
          "moduleId": 75708,
          "async": false,
          "exportedName": "updateTeamContactInfoAction",
          "filename": "features/teams/actions.ts"
        }
      },
      "layer": {
        "app/(public)/team/page": "action-browser"
      },
      "exportedName": "updateTeamContactInfoAction",
      "filename": "features/teams/actions.ts"
    },
    "400217ed9ab5c493fdbf2f4d38173565a2098f8e06": {
      "workers": {
        "app/(public)/team/page": {
          "moduleId": 75708,
          "async": false,
          "exportedName": "updatePlayerPersonalDetailsAction",
          "filename": "features/teams/actions.ts"
        }
      },
      "layer": {
        "app/(public)/team/page": "action-browser"
      },
      "exportedName": "updatePlayerPersonalDetailsAction",
      "filename": "features/teams/actions.ts"
    },
    "001c8e291feadcf4c7b4f7ed15ae7231d2ff7a2ed4": {
      "workers": {
        "app/(public)/team/page": {
          "moduleId": 75708,
          "async": false,
          "exportedName": "getHeroesAction",
          "filename": "features/players/actions.ts"
        }
      },
      "layer": {
        "app/(public)/team/page": "action-browser"
      },
      "exportedName": "getHeroesAction",
      "filename": "features/players/actions.ts"
    }
  },
  "edge": {}
}